{
  "display": {
    "icon": {
      "item": "hamburger:duck_butt"
    },
    "title": {
      "translate": "advancements.hamburger.duck_butt.title"
    },
    "description": {
      "translate": "advancements.hamburger.duck_butt.description"
    }
  },
  "parent": "hamburger:hamburger/the_same_toilet",
  "criteria": {
    "get_duck_butt": {
      "trigger": "minecraft:inventory_changed",
      "conditions": {
        "items": [
          {
            "item": "hamburger:duck_butt"
          }
        ]
      }
    }
  }
}